QuackGrad/TensorClass.py
QuackGrad/__init__.py
QuackGrad/Ops/__init__.py
QuackGrad/Ops/basic.py
QuackGrad/Ops/matrix.py
QuackGrad/Ops/statistics.py
quackgrad-0.1.0.dist-info/METADATA
quackgrad-0.1.0.dist-info/WHEEL
quackgrad-0.1.0.dist-info/top_level.txt
quackgrad-0.1.0.dist-info/RECORD
