Metadata-Version: 2.4
Name: QuackGrad
Version: 0.1.0
Summary: A simple auto-grad engine.
Author: SirQuackPng
Requires-Python: >=3.7
Requires-Dist: numpy
Dynamic: author
Dynamic: requires-dist
Dynamic: requires-python
Dynamic: summary
